relace_agent/__init__.py
relace_agent/agents.py
relace_agent/config.py
relace_agent/context.py
relace_agent/errors.py
relace_agent/server/__init__.py
relace_agent/server/types.py
relace_mcp/__init__.py
relace_mcp/main.py
relace_toolbox/__init__.py
relace_toolbox/errors.py
relace_toolbox/local_client.py
relace_toolbox/py.typed
relace_toolbox/tools.py
relace_toolbox/types.py
relace_mcp_server-0.1.5.dist-info/METADATA
relace_mcp_server-0.1.5.dist-info/WHEEL
relace_mcp_server-0.1.5.dist-info/entry_points.txt
relace_mcp_server-0.1.5.dist-info/RECORD
