Metadata-Version: 2.4
Name: relace-mcp-server
Version: 0.1.5
Summary: Relace MCP server
Requires-Python: >=3.13
Requires-Dist: aiofile>=3.9.0
Requires-Dist: aiofiles>=25.1.0
Requires-Dist: fastmcp>=2.14.0
Requires-Dist: httpx>=0.28.1
Requires-Dist: openai>=2.11.0
Requires-Dist: pydantic-yaml>=1.6.0
Requires-Dist: pydantic>=2.12.5
Requires-Dist: relace>=1.3.0
